sshkp/__init__.py
sshkp/__main__.py
sshkp/cli.py
sshkp-1.2.dist-info/LICENSE
sshkp-1.2.dist-info/METADATA
sshkp-1.2.dist-info/WHEEL
sshkp-1.2.dist-info/entry_points.txt
sshkp-1.2.dist-info/top_level.txt
sshkp-1.2.dist-info/RECORD
